{"ru": 4345448, "com": 432357, "ua": 572228, "info": 227608, "net": 191347, "au": 1325, "tk": 11078, "by": 96291, "su": 56145, "name": 4739, "travel": 1254, "co": 1144, "pro": 12066, "kz": 48573, "cz": 4195, "org": 84909, "tv": 11116, "cc": 1996, "ga": 1025, "sh": 24, "de": 12909, "uk": 3820, "fr": 3202, "lt": 1835, "am": 1894, "il": 13998, "club": 3263, "no": 1284, "nl": 4968, "tr": 3055, "live": 12, "ie": 1282, "kr": 1014, "kg": 4820, "it": 4054, "tm": 371, "store": 2, "biz": 18897, "pe": 20, "center": 735, "uz": 5800, "press": 107, "me": 9480, "es": 3113, "md": 7266, "lv": 5381, "xn--p1ai": 3964, "ee": 2731, "eu": 5047, "az": 2273, "tj": 1473, "gq": 354, "ink": 223, "xxx": 408, "guide": 40, "fi": 2824, "sk": 462, "hk": 1193, "cf": 615, "in": 3841, "tw": 849, "bg": 1085, "be": 1631, "ch": 1971, "mobi": 832, "mx": 399, "pw": 701, "ae": 514, "gr": 2361, "cash": 10, "moda": 41, "xyz": 729, "ws": 4689, "online": 709, "xn--80asehdb": 44, "br": 821, "pl": 1893, "top": 403, "ro": 1638, "st": 45, "link": 196, "fm": 1271, "ca": 2023, "hu": 2208, "jp": 1188, "moscow": 1114, "im": 504, "tel": 165, "video": 33, "estate": 24, "at": 2276, "sg": 436, "accountant": 747, "nz": 471, "se": 2732, "cn": 301, "do": 19, "cy": 97, "aero": 253, "academy": 71, "ninja": 174, "tatar": 44, "ke": 178, "pt": 1075, "ge": 703, "hr": 287, "ar": 964, "news": 1747, "us": 1022, "dk": 465, "lc": 10, "today": 750, "land": 151, "expert": 112, "tf": 2, "life": 280, "guru": 716, "agency": 101, "uno": 4, "clinic": 47, "company": 219, "ooo": 18, "ml": 528, "cr": 9, "audio": 41, "red": 41, "ir": 38, "ag": 14, "space": 185, "io": 172, "bio": 16, "xn--c1avg": 5, "bz": 341, "city": 320, "si": 147, "site": 174, "tattoo": 13, "re": 296, "gd": 39, "events": 11, "asia": 277, "ms": 119, "int": 14, "za": 36, "wiki": 93, "my": 85, "win": 45, "gift": 42, "zone": 377, "vision": 8, "town": 7, "direct": 26, "equipment": 3, "world": 21, "museum": 21, "casino": 2, "rs": 481, "gg": 42, "mk": 95, "ai": 32, "gdn": 7, "menu": 49, "pub": 7, "sx": 56, "to": 182, "ph": 5, "parts": 5, "cl": 45, "gallery": 45, "tn": 2, "photo": 23, "global": 11, "mn": 51, "market": 129, "work": 31, "media": 214, "moe": 19, "xn--90ais": 31, "html": 9, "so": 40, "ug": 9, "vc": 89, "shoes": 75, "ad": 4, "pet": 4, "li": 73, "xn--j1amh": 30, "care": 31, "sale": 428, "boutique": 30, "cd": 27, "rip": 113, "eg": 85, "ng": 14, "taxi": 8, "house": 53, "best": 7, "lk": 7, "rocks": 22, "bike": 46, "style": 14, "vu": 3, "place": 1, "restaurant": 4, "dj": 5, "loan": 3, "wtf": 147, "ec": 13, "plus": 16, "works": 3, "one": 41, "cm": 4, "xn--d1acj3b": 6, "consulting": 6, "archi": 3, "trade": 14, "holiday": 18, "shop": 14, "nu": 28, "bar": 6, "vip": 3, "click": 32, "engineering": 5, "berlin": 26, "ba": 13, "casa": 7, "edu": 54, "social": 119, "education": 29, "wf": 16, "mt": 37, "gt": 2, "vn": 41, "nyc": 26, "xn--80adxhks": 35, "lighting": 29, "ac": 12, "toys": 25, "courses": 9, "tools": 7, "help": 16, "voyage": 14, "studio": 20, "vg": 6, "domains": 4, "website": 26, "al": 6, "deals": 1, "la": 71, "lawyer": 2, "id": 33, "is": 26, "gs": 51, "th": 10, "xn--80ao21a": 2, "sr": 10, "credit": 8, "ly": 21, "church": 1, "sexy": 46, "mg": 28, "bid": 11, "london": 5, "cafe": 1, "systems": 16, "cards": 3, "show": 1, "team": 5, "marketing": 3, "clothing": 3, "camp": 2, "cool": 15, "hosting": 6, "tech": 6, "fit": 6, "cx": 12, "chat": 4, "tt": 2, "tc": 7, "rent": 15, "dm": 8, "lu": 10, "money": 5, "rest": 3, "black": 4, "gov": 5, "digital": 7, "graphics": 2, "discount": 1, "cat": 14, "report": 8, "wien": 1, "delivery": 10, "country": 13, "tl": 4, "florist": 2, "mu": 7, "jewelry": 4, "cu": 4, "beer": 1, "foundation": 9, "zm": 1, "fish": 8, "email": 1, "institute": 17, "yt": 2, "law": 5, "dog": 1, "design": 12, "cheap": 1, "international": 1, "php": 2, "porn": 8, "jo": 2, "ma": 7, "school": 1, "htm": 3, "xlsx": 1, "ovh": 3, "pics": 2, "yandex": 1, "buzz": 4, "film": 24, "capital": 7, "photos": 7, "furniture": 4, "fashion": 1, "reviews": 4, "science": 1, "business": 2, "catering": 1, "xn--80aswg": 6, "democrat": 3, "coop": 5, "exe": 1, "run": 8, "solutions": 8, "bank": 1, "vet": 1, "tennis": 1, "bo": 2, "host": 1, "sc": 4, "tips": 3, "farm": 2, "pm": 10, "support": 6, "community": 1, "directory": 3, "uy": 4, "partners": 1, "kitchen": 6, "ht": 4, "pk": 3, "legal": 4, "yoga": 17, "management": 6, "dating": 3, "tours": 1, "dance": 2, "coffee": 8, "apartments": 3, "investments": 5, "xn--p1acf": 3, "blue": 2, "ngo": 1, "pictures": 1, "koeln": 1, "wang": 1, "camera": 3, "insure": 1, "party": 1, "bet": 3, "pn": 5, "build": 1, "exchange": 3, "family": 1, "jobs": 1, "services": 1, "miami": 2, "recipes": 1, "lol": 2, "fishing": 2, "kim": 1, "watch": 3, "sd": 1, "gold": 3, "software": 2, "sa": 1, "network": 1, "photography": 1, "fund": 1, "eus": 1, "webcam": 1, "dental": 1, "sex": 4, "bt": 1, "energy": 3, "hamburg": 2, "pa": 1, "pink": 1, "industries": 1, "careers": 1, "cg": 1, "dz": 1, "mc": 2, "university": 5, "productions": 1, "files": 1, "hn": 1, "gy": 1, "fitness": 2, "rentals": 1}