{"com": 3290713, "nl": 18993, "ie": 21932, "ca": 75667, "org": 446608, "ch": 7368, "edu": 80425, "solutions": 383, "jp": 4687, "in": 43432, "club": 3605, "info": 25185, "nz": 7095, "net": 169770, "de": 31106, "ug": 1080, "gr": 5302, "at": 3917, "au": 24073, "cn": 4115, "ph": 5097, "tv": 9484, "is": 1553, "coffee": 154, "zw": 668, "se": 6371, "fr": 11858, "land": 182, "ke": 3785, "pl": 14762, "no": 3366, "be": 6939, "bn": 75, "mil": 943, "int": 813, "sg": 7338, "uk": 34594, "es": 6998, "io": 18116, "mobi": 1188, "top": 2604, "online": 5496, "id": 3709, "nu": 986, "site": 1225, "vn": 4004, "ga": 583, "us": 18064, "ru": 9278, "ua": 1449, "pk": 6497, "me": 11181, "xyz": 9145, "social": 247, "pt": 2006, "co": 22526, "shop": 3933, "kr": 1786, "cz": 5565, "pw": 549, "fun": 549, "cl": 1535, "ba": 329, "ro": 3131, "np": 684, "it": 16303, "ngo": 182, "sz": 38, "lt": 1206, "rs": 1272, "asia": 1664, "qa": 362, "fyi": 164, "th": 825, "life": 1535, "blog": 11691, "world": 1310, "mz": 69, "al": 324, "bg": 846, "audio": 131, "ai": 2419, "my": 5586, "management": 20, "dance": 69, "li": 170, "studio": 589, "community": 414, "google": 38, "biz": 7404, "ls": 68, "fm": 3383, "bm": 168, "uz": 153, "vote": 38, "gov": 20404, "school": 201, "ng": 8202, "cloud": 684, "ae": 3350, "eu": 22835, "report": 268, "cm": 67, "network": 604, "finance": 186, "jobs": 294, "sbs": 97, "company": 162, "run": 204, "app": 6932, "dk": 3898, "vision": 73, "best": 429, "work": 347, "london": 767, "news": 6271, "wales": 515, "win": 652, "vc": 290, "blue": 85, "ly": 733, "za": 2496, "bet": 84, "website": 1117, "mt": 878, "desi": 35, "cc": 3357, "cf": 513, "scot": 1181, "jm": 112, "tw": 1050, "media": 1406, "tr": 1341, "store": 1962, "art": 1341, "global": 836, "money": 99, "lol": 99, "mm": 158, "pet": 62, "br": 984, "farm": 154, "tips": 327, "health": 331, "church": 901, "dev": 1743, "mk": 537, "sa": 804, "fi": 3742, "love": 222, "vip": 644, "reviews": 276, "dating": 108, "tn": 244, "ooo": 55, "institute": 102, "bt": 140, "live": 2131, "events": 217, "su": 439, "one": 1035, "link": 685, "aero": 494, "agency": 703, "baby": 18, "space": 1306, "gi": 197, "kw": 166, "uno": 56, "ee": 1572, "ovh": 56, "mu": 271, "press": 484, "gg": 1047, "hu": 2225, "ir": 1787, "name": 716, "llc": 51, "si": 1241, "coop": 639, "pics": 190, "guru": 479, "bd": 789, "ar": 1006, "cat": 794, "immo": 19, "pro": 2828, "ge": 676, "healthcare": 52, "az": 676, "hr": 1158, "travel": 844, "tech": 1402, "college": 49, "wiki": 785, "hk": 3648, "tours": 93, "ltd": 192, "mx": 787, "icu": 126, "stream": 175, "coach": 100, "care": 239, "lv": 979, "tax": 52, "group": 398, "legal": 166, "lb": 223, "cyou": 181, "boutique": 134, "beer": 117, "am": 898, "today": 1312, "saarland": 12, "moe": 126, "et": 80, "photos": 152, "gifts": 49, "cr": 116, "re": 172, "lawyer": 37, "marketing": 191, "buzz": 249, "sydney": 56, "foundation": 153, "digital": 502, "ck": 21, "games": 482, "academy": 504, "cards": 67, "fashion": 84, "lu": 822, "lk": 1836, "video": 434, "cu": 96, "gq": 434, "uy": 101, "gallery": 244, "design": 661, "bank": 198, "physio": 29, "md": 460, "support": 114, "kz": 485, "page": 329, "plus": 224, "gh": 571, "city": 363, "mo": 111, "review": 116, "iq": 160, "aws": 31, "cy": 701, "bz": 316, "film": 96, "ac": 158, "cw": 29, "tk": 1016, "bio": 192, "zm": 108, "afl": 7, "tz": 349, "to": 1010, "ink": 212, "cafe": 163, "ws": 792, "clothing": 44, "tools": 141, "fj": 259, "watch": 189, "insure": 29, "bar": 51, "christmas": 12, "il": 1067, "gt": 47, "graphics": 29, "rw": 132, "click": 248, "monster": 149, "business": 140, "zone": 343, "la": 493, "center": 193, "pe": 371, "museum": 132, "berlin": 177, "rest": 57, "place": 65, "market": 138, "do": 201, "ventures": 73, "py": 52, "swiss": 127, "partners": 72, "sk": 1359, "kitchen": 65, "technology": 146, "services": 109, "mv": 181, "email": 80, "ninja": 241, "codes": 170, "photography": 446, "eus": 308, "africa": 715, "dj": 18, "nyc": 630, "ml": 384, "properties": 49, "builders": 98, "eco": 132, "party": 60, "university": 78, "rocks": 434, "host": 89, "solar": 43, "directory": 175, "construction": 24, "basketball": 71, "cern": 23, "miami": 64, "na": 328, "pm": 135, "wine": 183, "by": 364, "property": 16, "vu": 69, "im": 383, "ag": 191, "af": 281, "deals": 144, "fit": 279, "mba": 24, "beauty": 16, "je": 229, "law": 508, "fish": 65, "fitness": 112, "webcam": 81, "xn--p1ai": 141, "xxx": 121, "works": 173, "garden": 27, "delivery": 22, "glass": 46, "eg": 369, "ma": 254, "dentist": 26, "golf": 89, "cool": 82, "mc": 74, "help": 319, "sb": 73, "cx": 122, "tokyo": 178, "house": 135, "earth": 165, "singles": 11, "ni": 30, "green": 58, "style": 116, "realestate": 63, "luxury": 61, "wtf": 166, "capital": 105, "vegas": 111, "kg": 99, "expert": 184, "vet": 60, "sy": 104, "gdn": 3, "consulting": 137, "onl": 163, "kpmg": 72, "pub": 261, "capetown": 38, "actor": 25, "tf": 68, "yoga": 60, "bible": 49, "download": 147, "frl": 7, "kh": 120, "ren": 9, "bw": 134, "team": 122, "cymru": 202, "cam": 198, "fo": 64, "build": 45, "sale": 65, "education": 307, "restaurant": 27, "tube": 211, "software": 91, "gm": 138, "toys": 43, "sandvik": 12, "shopping": 53, "international": 156, "rehab": 14, "COM": 9, "town": 74, "brussels": 68, "so": 172, "auction": 30, "chat": 115, "sl": 69, "ht": 73, "ps": 118, "tt": 197, "engineer": 10, "guide": 466, "red": 92, "bond": 18, "realtor": 113, "cricket": 46, "pr": 70, "organic": 5, "bs": 55, "fans": 41, "energy": 116, "pictures": 85, "ms": 117, "dental": 64, "systems": 108, "om": 104, "sh": 163, "rugby": 60, "accountants": 9, "ve": 74, "gal": 37, "ec": 133, "st": 289, "rodeo": 23, "sharp": 3, "pharmacy": 21, "gy": 147, "hockey": 29, "estate": 41, "tm": 91, "hosting": 28, "fan": 37, "tel": 25, "krd": 34, "casino": 58, "day": 45, "surf": 47, "tl": 111, "wf": 21, "archi": 19, "mn": 190, "sx": 26, "bid": 45, "direct": 107, "dz": 59, "recipes": 144, "cpa": 55, "mom": 54, "movie": 50, "careers": 129, "amsterdam": 63, "weber": 11, "paris": 63, "bo": 57, "bike": 148, "wedding": 31, "mg": 15, "quest": 39, "ski": 21, "engineering": 55, "pf": 5, "bayern": 3, "realty": 19, "forsale": 23, "flowers": 7, "training": 149, "camp": 57, "courses": 28, "sr": 21, "shoes": 40, "cv": 33, "irish": 56, "homes": 48, "osaka": 1, "kiwi": 116, "menu": 30, "cooking": 11, "plumbing": 14, "photo": 135, "as": 91, "pa": 68, "sex": 39, "trade": 79, "band": 84, "science": 174, "jo": 204, "family": 75, "ky": 161, "ong": 5, "porn": 41, "bh": 112, "sport": 90, "exchange": 76, "gold": 28, "clinic": 66, "durban": 3, "furniture": 34, "soy": 1, "pg": 103, "equipment": 31, "gl": 44, "football": 46, "rentals": 31, "apartments": 3, "casa": 70, "lc": 19, "lgbt": 54, "ci": 42, "tickets": 10, "show": 115, "canon": 31, "date": 40, "lighting": 29, "cleaning": 9, "kaufen": 3, "doctor": 10, "domains": 39, "joburg": 3, "cash": 63, "repair": 38, "bb": 42, "gmbh": 3, "wien": 16, "vin": 11, "game": 33, "sn": 51, "cheap": 12, "bargains": 14, "taipei": 21, "hair": 19, "adult": 4, "gs": 56, "exposed": 22, "cd": 38, "sc": 102, "industries": 22, "melbourne": 44, "NET": 2, "limited": 14, "saxo": 43, "discount": 15, "pink": 35, "diamonds": 22, "fail": 7, "bf": 16, "ao": 13, "productions": 39, "sm": 29, "poker": 8, "moda": 18, "florist": 11, "neustar": 4, "xn--h2brj9c": 3, "express": 30, "tj": 26, "abudhabi": 8, "radio": 108, "lr": 21, "dog": 69, "nc": 20, "parts": 46, "loans": 24, "gift": 37, "financial": 36, "rip": 22, "cruises": 12, "tirol": 25, "surgery": 7, "salon": 15, "shiksha": 14, "yachts": 4, "inc": 35, "html": 4, "yokohama": 4, "coupons": 8, "fund": 55, "kn": 26, "vi": 34, "limo": 6, "cfd": 22, "hamburg": 15, "taxi": 11, "racing": 34, "men": 47, "fk": 10, "how": 64, "vg": 80, "security": 21, "va": 56, "dm": 14, "dhl": 2, "alsace": 36, "mw": 89, "fishing": 14, "computer": 12, "tc": 41, "kpn": 2, "loan": 17, "autos": 13, "cars": 22, "tienda": 17, "kyoto": 6, "rent": 29, "blackfriday": 1, "bi": 22, "condos": 2, "charity": 13, "supply": 32, "sd": 24, "gop": 44, "istanbul": 7, "youtube": 9, "aw": 6, "degree": 1, "kp": 3, "investments": 12, "ismaili": 9, "moscow": 14, "auto": 22, "nrw": 21, "enterprises": 12, "observer": 41, "wang": 8, "diet": 14, "vacations": 13, "gp": 11, "skin": 11, "study": 16, "php": 10, "bzh": 19, "country": 10, "guitars": 6, "horse": 12, "sv": 15, "shell": 2, "black": 30, "tennis": 9, "bot": 15, "ist": 18, "gay": 35, "ad": 25, "holiday": 26, "barclays": 9, "ax": 11, "honda": 2, "voyage": 9, "mortgage": 7, "flights": 12, "soccer": 5, "haus": 8, "panasonic": 2, "teva": 2, "supplies": 19, "mr": 17, "okinawa": 4, "barcelona": 14, "lat": 4, "ricoh": 1, "gripe": 11, "hospital": 10, "gd": 44, "career": 11, "yt": 16, "insurance": 5, "lease": 1, "boston": 8, "jewelry": 21, "pn": 1, "claims": 4, "bingo": 4, "contractors": 12, "km": 2, "storage": 2, "java": 3, "camera": 14, "tg": 4, "xn--j1amh": 8, "ye": 4, "gent": 13, "markets": 23, "memorial": 6, "ntt": 7, "crs": 5, "corsica": 13, "aquarelle": 3, "tattoo": 17, "sony": 3, "hm": 3, "brother": 1, "aco": 3, "mp": 9, "army": 10, "kids": 2, "navy": 2, "attorney": 13, "cab": 9, "quebec": 24, "futbol": 3, "faith": 20, "trading": 6, "associates": 12, "sexy": 11, "villas": 14, "boats": 5, "post": 3, "hiv": 1, "bj": 10, "kim": 13, "bnpparibas": 19, "holdings": 3, "srl": 4, "abogado": 3, "hn": 9, "pizza": 12, "nf": 3, "hiphop": 9, "xn--rvc1e0am3e": 1, "zuerich": 1, "hisamitsu": 1, "sener": 2, "reit": 1, "cologne": 3, "toshiba": 5, "aq": 6, "schule": 3, "ikano": 1, "gives": 6, "xn--czr694b": 1, "helsinki": 1, "feedback": 2, "gratis": 4, "epson": 1, "jetzt": 4, "ceo": 12, "aspx": 2, "ss": 3, "ORG": 4, "maison": 2, "promo": 8, "xn--80asehdb": 1, "accountant": 4, "credit": 4, "koeln": 2, "nagoya": 1, "stockholm": 1, "makeup": 3, "abbott": 2, "med": 4, "xn--tckwe": 1, "rsvp": 1, "catering": 5, "UK": 1, "vlaanderen": 2, "erni": 2, "xn--y9a3aq": 1, "ne": 1, "theater": 1, "forum": 1, "ruhr": 1, "gn": 1, "vanguard": 1, "next": 1, "praxi": 2, "sucks": 1, "rich": 1, "ryukyu": 1, "qpon": 2, "xn--90ais": 1, "contact": 1, "broker": 2, "softbank": 1, "sky": 2, "pictet": 1, "kred": 1, "toyota": 2, "hitachi": 2, "xin": 1, "tires": 1, "xn--q9jyb4c": 1, "car": 1, "gu": 2, "forex": 2, "cg": 1, "creditcard": 1, "xn--d1alf": 1, "td": 1, "seat": 1}