{"com": 3456431, "jp": 3561570, "au": 1414, "org": 176691, "biz": 97545, "net": 779178, "tokyo": 14201, "info": 144145, "ac": 1297, "in": 8476, "to": 10578, "xyz": 70883, "site": 6375, "co": 12972, "work": 3281, "sc": 6005, "cc": 19877, "tw": 7513, "tv": 29387, "link": 7029, "pl": 2230, "mobi": 3560, "la": 1249, "me": 34771, "cn": 16128, "space": 787, "yokohama": 1007, "it": 3742, "ai": 233, "shop": 1639, "sg": 1000, "pink": 2793, "travel": 601, "se": 499, "live": 185, "nagoya": 1001, "cz": 519, "club": 7099, "ph": 386, "online": 5442, "red": 1901, "nu": 858, "de": 1234, "press": 198, "ru": 2176, "is": 932, "io": 1910, "be": 2774, "click": 3961, "media": 907, "place": 54, "news": 307, "asia": 8034, "cm": 82, "ua": 388, "blue": 1089, "ch": 3960, "photo": 167, "mt": 183, "aero": 65, "sn": 5, "fm": 1890, "pro": 336, "fr": 1239, "mu": 1998, "blog": 1072, "pt": 2006, "uk": 2678, "coop": 1194, "global": 118, "tk": 951, "tc": 271, "us": 2437, "tips": 139, "es": 676, "bz": 2422, "pw": 1806, "clinic": 224, "pm": 299, "xn--tckwe": 501, "top": 2764, "plus": 208, "support": 116, "st": 1138, "dj": 35, "br": 3415, "okinawa": 877, "directory": 47, "im": 98, "cf": 309, "hk": 1216, "pet": 21, "nico": 154, "ga": 173, "one": 31, "wiki": 519, "agency": 23, "re": 125, "life": 1126, "mx": 305, "am": 451, "bj": 93, "tech": 388, "party": 38, "xn--fiqs8s": 30, "vc": 859, "mn": 150, "cl": 402, "lt": 356, "nl": 541, "il": 820, "fashion": 20, "cx": 471, "vg": 38, "ro": 713, "gs": 580, "ec": 731, "html": 449, "love": 50, "hn": 14, "dk": 79, "eu": 613, "ar": 315, "ws": 1535, "store": 148, "earth": 7, "kr": 1060, "garden": 12, "care": 12, "tours": 41, "canon": 53, "review": 146, "ca": 1247, "ms": 428, "style": 363, "sexy": 356, "vn": 772, "ug": 9, "social": 44, "name": 453, "world": 320, "rocks": 473, "at": 242, "id": 116, "win": 104, "house": 38, "tr": 276, "help": 69, "network": 122, "so": 161, "fun": 137, "md": 101, "cgi": 27, "osaka": 211, "hu": 92, "sandvik": 3, "games": 11, "tm": 30, "art": 39, "taipei": 29, "ink": 49, "photos": 61, "ryukyu": 115, "moe": 260, "si": 40, "edu": 294, "fund": 5, "events": 92, "lv": 268, "sk": 747, "website": 382, "mp": 39, "black": 367, "company": 164, "th": 312, "money": 75, "xn--q9jyb4c": 156, "phtml": 4, "recipes": 43, "kyoto": 236, "town": 205, "wedding": 47, "vet": 74, "bm": 327, "gallery": 129, "today": 522, "my": 141, "yoga": 48, "aspx": 16, "ninja": 135, "gift": 200, "jobs": 10, "zone": 34, "nz": 548, "beer": 21, "ag": 76, "coffee": 21, "vision": 20, "gm": 113, "ve": 162, "li": 53, "london": 7, "ceo": 129, "qa": 2, "sh": 178, "design": 60, "city": 143, "vip": 62, "museum": 66, "cloud": 30, "pics": 87, "works": 85, "community": 5, "gr": 32, "pe": 15, "cat": 10, "dog": 32, "cafe": 49, "int": 15, "ke": 64, "cd": 10, "diet": 35, "az": 41, "cooking": 4, "xxx": 79, "dental": 34, "np": 137, "php": 139, "hm": 125, "ba": 7, "lighting": 3, "services": 12, "asp": 14, "accountant": 14, "host": 39, "mo": 36, "htm": 27, "video": 11, "ovh": 117, "fi": 84, "stream": 6, "kw": 1, "kitchen": 14, "salon": 22, "business": 4, "kz": 37, "center": 72, "education": 20, "direct": 30, "ooo": 40, "school": 16, "nyc": 26, "rest": 10, "fish": 22, "photography": 12, "theater": 17, "wang": 7, "cards": 7, "pictures": 10, "mom": 3, "fitness": 8, "university": 25, "land": 17, "bar": 37, "ml": 32, "eg": 1, "careers": 69, "run": 40, "by": 35, "no": 22, "audio": 40, "ge": 5, "promo": 1, "su": 19, "mk": 67, "expert": 69, "lawyer": 1, "science": 44, "ir": 52, "technology": 16, "date": 38, "ma": 34, "onl": 36, "uy": 32, "holiday": 44, "marketing": 21, "holdings": 29, "hosting": 13, "archi": 3, "dnp": 14, "insure": 2, "academy": 39, "gl": 3, "camp": 31, "gov": 32, "equipment": 3, "cfm": 6, "guide": 53, "dance": 29, "team": 8, "lgbt": 27, "report": 10, "va": 18, "tax": 7, "restaurant": 4, "ly": 13, "international": 13, "gives": 6, "tools": 15, "golf": 39, "guitars": 12, "fo": 2, "studio": 26, "family": 12, "gratis": 8, "solutions": 23, "za": 53, "fit": 8, "band": 15, "ie": 15, "tn": 29, "gold": 16, "rip": 2, "rs": 12, "download": 37, "estate": 26, "camera": 8, "hr": 18, "uno": 7, "xn--p1ai": 10, "associates": 15, "group": 10, "as": 18, "ricoh": 4, "coach": 18, "gq": 20, "trade": 2, "ventures": 6, "articleView": 3, "lc": 9, "lol": 6, "ae": 5, "gdn": 14, "memorial": 20, "farm": 9, "guru": 5, "game": 2, "je": 5, "partners": 13, "saxo": 14, "form": 1, "market": 8, "uz": 3, "singles": 19, "wine": 8, "ee": 17, "men": 1, "legal": 4, "reviews": 8, "pk": 13, "bid": 6, "jsp": 4, "bike": 49, "mv": 2, "tienda": 2, "flowers": 4, "fishing": 2, "ren": 7, "shoes": 5, "na": 2, "cool": 3, "boutique": 2, "software": 4, "paris": 8, "nf": 9, "wien": 2, "training": 2, "kg": 5, "film": 1, "komatsu": 4, "rent": 1, "bi": 2, "systems": 4, "tt": 2, "do": 6, "bg": 1, "jewelry": 3, "glass": 2, "tires": 1, "clothing": 3, "pn": 3, "jo": 1, "ps": 1, "ist": 1, "engineer": 7, "lu": 5, "digital": 2, "auction": 3, "jhtml": 2, "moscow": 3, "rb": 1, "tattoo": 5, "toys": 1, "football": 7, "cu": 1, "casa": 2, "hiphop": 1, "lk": 2, "tennis": 4, "builders": 1, "cash": 3, "ad": 1, "kim": 1, "Html": 1, "computer": 2, "productions": 2, "jspx": 1, "mr": 8, "bo": 2, "church": 2, "fj": 2, "toray": 1, "engineering": 1, "gg": 4, "ht": 1, "ntt": 1, "consulting": 1, "loan": 3, "swiss": 2, "college": 3, "action": 1, "organic": 1, "foundation": 2, "study": 1, "law": 2, "kiwi": 3, "py": 2, "chat": 2, "ltd": 1, "gt": 2, "capital": 1, "ng": 1, "gy": 1, "pg": 1, "sony": 1, "bd": 1, "ski": 1, "graphics": 1, "tl": 1, "xin": 1, "porn": 1, "mil": 2, "berlin": 1, "racing": 1, "kh": 1}