{"com": 3466949, "net": 236114, "cn": 762652, "in": 699, "today": 91, "org": 102423, "info": 9327, "cc": 99241, "me": 3681, "la": 5824, "so": 5909, "tv": 9826, "ch": 9, "fr": 324, "hk": 2271, "us": 913, "ca": 1828, "kr": 60, "biz": 4213, "de": 304, "eu": 326, "jp": 1003, "fm": 544, "pt": 19, "lu": 30, "vn": 28, "nz": 123, "do": 7, "sg": 258, "co": 8946, "au": 316, "my": 290, "pro": 57, "asia": 3046, "tw": 2076, "mobi": 266, "aspx": 21, "tf": 1, "pw": 59, "li": 19, "xyz": 57, "vc": 50, "ws": 18, "cm": 624, "cl": 4, "kz": 1, "im": 332, "za": 66, "name": 491, "at": 38, "rs": 7, "ru": 109, "jsp": 16, "br": 7, "si": 46, "mx": 38, "sp": 1, "nl": 11, "top": 47, "sk": 6, "php": 32, "shtml": 8, "uk": 48, "fi": 4, "nu": 16, "es": 46, "travel": 21, "tk": 6, "io": 97, "edu": 17, "bz": 56, "ie": 6, "to": 11, "htm": 16, "cr": 1, "it": 61, "dk": 6, "pk": 16, "tm": 22, "se": 328, "sh": 6, "gg": 32, "pa": 2, "gl": 4, "club": 8, "html": 95, "re": 3, "wang": 35, "lv": 17, "ba": 39, "sm": 1, "jobs": 62, "gy": 7, "gr": 18, "ml": 3, "ee": 3, "asp": 32, "be": 9, "su": 9, "ejf": 2, "lt": 4, "ly": 4, "ren": 9, "cd": 4, "il": 4, "sexy": 1, "pl": 39, "sy": 3, "sc": 11, "az": 7, "moe": 1, "cz": 10, "pics": 6, "id": 1, "ua": 3, "mm": 2, "museum": 1, "gp": 2, "tc": 10, "mk": 1, "action": 6, "sv": 1, "ac": 4, "hu": 5, "ro": 1, "sa": 1, "int": 4, "xn--fiqs8s": 11, "ax": 1, "is": 2, "ir": 4, "jhtml": 2, "jspx": 2, "gd": 9, "ms": 1, "ae": 1, "jspy": 2, "xxx": 3, "lc": 1, "qa": 1, "tr": 1, "am": 2, "wiki": 1, "ph": 4, "mc": 2, "je": 1, "DaFang": 1, "gov": 4, "zone": 1, "th": 1, "mo": 1, "ec": 1, "ga": 1, "tt": 1, "va": 1}