{"com": 2468184, "cn": 786159, "net": 225173, "cc": 32125, "be": 67, "org": 77049, "la": 2279, "tv": 9230, "info": 11733, "me": 13869, "hk": 3109, "ru": 498, "top": 59655, "xyz": 1104, "in": 685, "jp": 3563, "us": 3693, "tw": 3029, "sg": 2641, "pro": 172, "biz": 4905, "fr": 654, "ca": 2435, "it": 438, "moe": 205, "de": 805, "trade": 715, "club": 7781, "loan": 974, "my": 5904, "cx": 129, "so": 608, "mobi": 251, "li": 96, "io": 1638, "school": 12, "asia": 310, "au": 1046, "wang": 868, "pl": 99, "ltd": 41, "vn": 1612, "link": 325, "edu": 314, "im": 819, "fm": 540, "gr": 548, "men": 425, "win": 815, "work": 91, "vip": 389, "kr": 750, "nu": 41, "faith": 417, "space": 97, "pet": 73, "nz": 242, "se": 136, "fun": 305, "ly": 268, "bid": 132, "co": 1234, "cm": 106, "br": 307, "pt": 53, "mo": 115, "vin": 202, "ac": 35, "ren": 133, "cat": 13, "buzz": 138, "aspx": 284, "download": 51, "ge": 4, "ws": 219, "to": 40, "zone": 40, "htm": 119, "sb": 239, "tech": 123, "xn--fiqs8s": 112, "site": 414, "travel": 167, "uk": 601, "ch": 605, "name": 862, "review": 99, "Html": 11, "center": 174, "world": 92, "life": 75, "pw": 324, "pub": 27, "dk": 66, "lu": 171, "pk": 60, "html": 403, "ie": 15, "direct": 60, "today": 88, "php": 266, "eu": 312, "jsp": 79, "gdn": 184, "ve": 1, "news": 96, "cy": 12, "one": 15, "solutions": 17, "wtf": 3, "fi": 96, "dhl": 12, "cd": 43, "tk": 80, "company": 7, "network": 3, "sohu": 10, "articleView": 1, "cricket": 25, "ml": 57, "asp": 216, "bg": 18, "blog": 104, "do": 70, "show": 14, "love": 36, "business": 13, "ms": 38, "komatsu": 2, "am": 57, "vc": 121, "bz": 200, "es": 402, "lgbt": 6, "hu": 65, "cz": 189, "nl": 129, "int": 43, "ar": 22, "il": 16, "ph": 30, "jobs": 6, "tr": 36, "science": 15, "va": 39, "ink": 29, "host": 32, "sh": 79, "tf": 4, "wine": 111, "racing": 54, "ro": 35, "app": 8, "ee": 96, "by": 61, "st": 3, "ooo": 4, "lk": 8, "xxx": 10, "xn--55qx5d": 1, "py": 1, "gq": 29, "online": 49, "technology": 3, "jspx": 42, "date": 34, "tm": 47, "kim": 83, "ma": 21, "design": 10, "sony": 7, "ki": 25, "codes": 4, "at": 81, "kz": 34, "gratis": 27, "cl": 12, "shtml": 44, "action": 39, "re": 9, "jhtml": 51, "tools": 5, "gd": 13, "cool": 8, "no": 17, "porn": 6, "kh": 3, "canon": 1, "bet": 4, "lt": 97, "ua": 26, "cloud": 10, "is": 27, "agency": 19, "ga": 20, "mx": 24, "mn": 10, "gg": 23, "shop": 38, "kg": 24, "care": 8, "digital": 19, "party": 20, "lv": 12, "si": 14, "click": 28, "tt": 34, "za": 24, "uz": 3, "tn": 5, "bio": 1, "xin": 124, "global": 29, "id": 33, "help": 12, "wiki": 11, "photo": 6, "ai": 38, "red": 22, "az": 24, "international": 11, "photography": 11, "plus": 9, "eus": 4, "mc": 2, "md": 2, "melbourne": 1, "museum": 3, "place": 11, "holiday": 2, "website": 15, "hn": 3, "ba": 3, "tokyo": 12, "ir": 19, "studio": 33, "monash": 3, "unicom": 2, "sk": 6, "ae": 11, "property": 10, "guide": 4, "rocks": 15, "cf": 37, "gov": 18, "services": 7, "sc": 6, "tips": 6, "nyc": 2, "land": 8, "vet": 11, "academy": 2, "rip": 4, "auto": 1, "style": 2, "ec": 1, "th": 28, "cafe": 3, "su": 5, "rs": 8, "np": 2, "marketing": 4, "mk": 1, "hitachi": 1, "gs": 10, "express": 1, "vg": 9, "car": 1, "bi": 5, "bo": 3, "webcam": 3, "group": 10, "xn--xhq521b": 1, "uy": 2, "city": 5, "wf": 2, "xn--8y0a063a": 1, "gp": 1, "works": 1, "miami": 1, "house": 5, "sa": 8, "cash": 7, "pink": 3, "lc": 4, "xn--fiqz9s": 11, "sale": 1, "mg": 2, "hm": 4, "pm": 10, "ag": 3, "osaka": 1, "gl": 2, "chat": 1, "al": 3, "gallery": 1, "farm": 1, "pe": 2, "sy": 4, "eg": 2, "paris": 3, "community": 1, "citic": 7, "qa": 1, "ci": 7, "mu": 1, "media": 3, "dog": 2, "xn--rhqv96g": 1, "xn--q9jyb4c": 1, "xhtml": 2, "support": 3, "vu": 1, "guru": 3, "hr": 2, "coffee": 2, "art": 1, "xn--p1ai": 2, "run": 1, "live": 2, "je": 3, "earth": 2, "engineer": 3, "mom": 7, "epx": 1, "clinic": 1, "capital": 2, "ASPX": 1, "okinawa": 2, "graphics": 2, "video": 3, "lol": 2, "fj": 1, "mw": 1, "fund": 1, "press": 1, "tz": 1, "plumbing": 1, "gy": 1, "sx": 1, "ninja": 3, "study": 1, "camp": 2, "vm": 1, "accountant": 1, "villas": 1, "xn--io0a7i": 1, "sexy": 1, "mvc": 1, "swiss": 1, "tl": 1, "gh": 1, "nagoya": 1, "htmlx": 1, "engineering": 1, "Asp": 1, "store": 1, "berlin": 1, "bike": 1, "kyoto": 1}