{"cn": 1306713, "com": 1765724, "cc": 41019, "host": 423, "net": 13194, "org": 12793, "space": 156, "pw": 104, "top": 13110, "uk": 79, "club": 25325, "biz": 29956, "site": 1451, "tv": 584, "us": 2043, "eus": 1, "ren": 63, "bid": 35532, "business": 85, "info": 5552, "html": 74, "hk": 3187, "men": 1980, "co": 1167, "la": 244, "loan": 1854, "win": 1893, "webcam": 898, "fm": 26, "date": 779, "ltd": 95, "ink": 119, "science": 2472, "eu": 42, "ws": 11, "me": 485, "de": 52, "dating": 1, "my": 36, "au": 236, "click": 930, "cx": 349, "online": 204, "vip": 817, "city": 20, "tw": 204, "link": 346, "trade": 109, "stream": 130, "dk": 6, "xyz": 362, "io": 85, "cloud": 19, "xn--55qx5d": 24, "wang": 255, "asia": 940, "hitachi": 1, "fun": 107, "name": 46, "tech": 216, "jp": 86, "in": 747, "sh": 5, "aspx": 38, "ru": 3, "ca": 284, "blog": 24, "ch": 45, "rocks": 1, "shop": 66, "ge": 208, "mobi": 147, "cz": 3, "ico": 2, "sale": 8, "ga": 5, "nu": 1, "Aspx": 8, "sg": 54, "bg": 1, "lol": 1, "tips": 2, "jsp": 10, "pro": 44, "tt": 3, "store": 19, "review": 30, "tk": 14, "racing": 50, "xin": 142, "so": 64, "center": 20, "cm": 148, "company": 61, "ac": 1, "news": 185, "party": 46, "work": 37, "faith": 49, "action": 7, "ms": 5, "php": 32, "hu": 2, "nz": 17, "group": 51, "fr": 23, "cf": 19, "htm": 17, "gd": 7, "one": 13, "it": 31, "bike": 4, "xn--6qq986b3xl": 14, "design": 5, "pub": 21, "today": 7, "red": 15, "ee": 2, "gift": 2, "live": 4, "kim": 11, "download": 56, "cd": 9, "webs": 1, "cheap": 11, "asp": 14, "art": 3, "gs": 11, "im": 36, "gg": 2, "be": 24, "moe": 5, "mx": 4, "pl": 5, "cool": 16, "do": 18, "pk": 1, "ba": 13, "xn--fiqs8s": 4, "xn--hxt814e": 4, "wiki": 3, "vn": 6, "vc": 8, "xn--czru2d": 37, "lt": 3, "gold": 7, "cat": 6, "ma": 1, "bz": 4, "fish": 1, "kr": 15, "life": 7, "lu": 3, "es": 19, "nl": 8, "at": 12, "ly": 7, "berlin": 1, "br": 2, "movie": 4, "cl": 4, "school": 3, "media": 2, "xn--kput3i": 11, "world": 5, "app": 3, "vg": 4, "cy": 2, "no": 2, "bet": 5, "blue": 3, "ag": 1, "is": 17, "DaFang": 1, "frl": 1, "lv": 1, "sc": 7, "social": 1, "tg": 1, "ml": 3, "jhtml": 5, "help": 2, "il": 1, "se": 10, "ph": 3, "xn--ses554g": 15, "vin": 3, "si": 1, "fi": 7, "gr": 4, "xn--rhqv96g": 1, "ua": 4, "love": 3, "gq": 4, "education": 2, "edu": 1, "accountant": 2, "vacations": 1, "website": 14, "technology": 2, "travel": 3, "jspx": 6, "hd": 1, "guide": 1, "sk": 1, "li": 2, "kw": 2, "games": 1, "by": 3, "gl": 2, "abbott": 3, "coupons": 1, "engineer": 1, "ie": 1, "ooo": 2, "tm": 3, "wtf": 1, "pm": 3, "hr": 1, "photo": 1, "lawyer": 6, "shtml": 1, "tax": 1, "sb": 6, "pt": 3, "pe": 1, "direct": 2, "mn": 1, "studio": 3, "mo": 2, "citic": 3, "team": 1, "xn--3ds443g": 3, "lc": 2, "th": 2, "capital": 1, "care": 2, "mw": 1, "lgbt": 1, "xn--io0a7i": 1, "taipei": 1, "tf": 1, "college": 8, "xn--55qw42g": 2, "ai": 2, "chat": 1, "codes": 1, "run": 1, "tel": 2, "tokyo": 1, "sex": 1, "style": 1, "network": 2, "ci": 2}