{"org": 19879, "com": 82379, "de": 2736, "net": 6523, "co": 607, "uk": 4837, "to": 278, "ru": 2684, "it": 924, "nl": 989, "ie": 990, "ro": 459, "mobi": 282, "is": 52, "fr": 1510, "ua": 352, "me": 1994, "ph": 46, "eu": 583, "ee": 50, "us": 364, "info": 1072, "tv": 975, "sg": 313, "cn": 1609, "audio": 1, "au": 1608, "asia": 30, "at": 635, "pl": 546, "es": 1045, "ch": 466, "edu": 110, "tw": 339, "guru": 3, "jp": 541, "mn": 12, "hk": 192, "in": 1504, "fm": 80, "dk": 464, "ir": 203, "biz": 1159, "ca": 1085, "jobs": 24, "br": 1329, "my": 94, "xyz": 519, "se": 343, "az": 15, "vn": 304, "cz": 337, "ws": 34, "hu": 164, "md": 22, "si": 24, "no": 154, "nu": 46, "cd": 2, "lk": 44, "gr": 413, "cl": 209, "kr": 311, "mx": 484, "pt": 273, "cc": 320, "company": 1, "tr": 263, "xxx": 422, "hr": 36, "red": 11, "io": 148, "be": 610, "gov": 7, "ml": 7, "ma": 47, "fi": 142, "pk": 60, "uz": 16, "il": 259, "xn--80asehdb": 1, "rocks": 10, "travel": 17, "ar": 512, "id": 212, "link": 43, "lv": 51, "nz": 253, "su": 80, "cat": 47, "bg": 89, "pe": 80, "tk": 65, "sn": 3, "watch": 1, "sc": 27, "directory": 1, "website": 1972, "ng": 30, "ec": 14, "pm": 2, "sk": 71, "aero": 3, "site": 2027, "win": 11339, "ae": 89, "za": 200, "loan": 921, "mk": 14, "faith": 2023, "top": 2217, "ly": 4, "online": 2054, "rs": 49, "scot": 205, "iq": 2, "lt": 395, "racing": 119, "pw": 65, "lb": 4, "date": 89, "by": 58, "name": 390, "bh": 1, "actor": 50, "bid": 49, "cf": 28, "ve": 20, "bio": 2, "download": 96, "do": 10, "accountant": 65, "la": 52, "agency": 3, "media": 3, "mt": 4, "computer": 6, "lu": 17, "ag": 13, "cricket": 23, "pro": 58, "bb": 3, "party": 24, "swiss": 2, "th": 37, "tn": 18, "kz": 131, "py": 16, "am": 10, "gq": 16, "ge": 11, "ke": 22, "host": 47, "ga": 15, "church": 2, "gt": 6, "life": 13, "im": 2, "al": 15, "ug": 9, "cr": 19, "gh": 17, "sexy": 4, "uy": 22, "club": 46, "furniture": 4, "vu": 1, "one": 1, "trade": 2, "li": 5, "eg": 9, "int": 2, "xn--p1ai": 5, "re": 3, "bd": 3, "construction": 2, "supply": 1, "mg": 1, "kg": 2, "press": 1, "koeln": 2, "men": 9, "tz": 11, "global": 3, "tt": 2, "mv": 1, "ni": 3, "fo": 1, "space": 54, "ac": 4, "bz": 5, "deals": 1, "html": 8, "beer": 2, "photos": 1, "ba": 5, "bo": 17, "moscow": 1, "st": 9, "mo": 5, "ps": 3, "ninja": 2, "care": 1, "as": 3, "webcam": 1, "np": 2, "sa": 6, "pf": 1, "today": 10, "gdn": 3, "so": 3, "band": 5, "cleaning": 1, "sd": 1, "services": 2, "consulting": 1, "gl": 1, "buzz": 1, "onl": 7, "sl": 1, "coach": 1, "solutions": 3, "ci": 4, "porn": 282, "asp": 2, "gg": 1, "sv": 3, "click": 9, "moe": 1, "dz": 1, "cymru": 1, "design": 1, "af": 2, "ovh": 1, "cy": 7, "paris": 2, "qa": 1, "properties": 1, "saarland": 1, "pics": 8, "live": 2, "education": 2, "london": 1, "nyc": 2, "xn--j1amh": 1, "institute": 1, "center": 2, "bt": 1, "work": 3, "land": 2, "direct": 1, "bm": 1, "tokyo": 1, "wiki": 2, "gallery": 1, "wang": 1, "bike": 1, "estate": 1, "photography": 1, "gm": 1, "bzh": 2, "lat": 1, "international": 1, "city": 1, "team": 1, "coop": 1, "business": 1, "news": 1, "pa": 3, "tj": 1, "berlin": 1, "bi": 1, "hosting": 1, "world": 23, "zone": 143, "mz": 1, "video": 22, "sex": 20, "support": 8, "green": 5, "tech": 4, "sx": 7, "hn": 1, "ms": 3, "gs": 1, "tf": 4, "menu": 1, "eus": 5, "store": 1, "kh": 1, "shop": 2, "et": 1, "gp": 1, "place": 1, "cafe": 1, "vc": 1, "email": 4, "vip": 1, "sy": 1, "ltd": 1, "ist": 1, "afl": 1, "rip": 1, "plus": 1, "php": 1, "aspx": 1, "sh": 1, "digital": 1, "blog": 1}