{"ru": 2188066, "com": 362196, "su": 36185, "pl": 13449, "net": 83210, "by": 72574, "kz": 50452, "tw": 95, "org": 69580, "pro": 16613, "info": 57144, "de": 5076, "travel": 1310, "me": 9193, "tv": 14454, "kg": 6718, "eu": 4919, "ca": 599, "ua": 126473, "xn--p1ai": 63257, "club": 10450, "top": 6249, "uz": 6555, "md": 6487, "name": 2816, "faith": 3, "news": 5738, "video": 421, "app": 609, "cc": 4115, "lt": 1747, "online": 16824, "site": 4007, "school": 286, "lv": 5456, "az": 4587, "space": 1248, "io": 4056, "store": 1880, "vision": 109, "fm": 3173, "cn": 632, "biz": 8589, "market": 1366, "guide": 128, "nl": 5054, "shop": 3475, "in": 2437, "one": 2469, "estate": 281, "ee": 5668, "fr": 3317, "it": 2165, "us": 853, "moscow": 2074, "xyz": 4290, "tj": 1356, "life": 2597, "tm": 229, "mobi": 1734, "sale": 267, "download": 22, "media": 6073, "agency": 501, "menu": 485, "tattoo": 7, "legal": 95, "guru": 3134, "press": 1455, "gr": 559, "rs": 177, "cy": 333, "xn--80adxhks": 595, "xn--90ais": 1196, "si": 67, "co": 2323, "cz": 4007, "am": 3581, "es": 1077, "to": 354, "science": 19, "toys": 115, "expert": 1016, "click": 439, "se": 350, "healthcare": 20, "ws": 2448, "today": 2691, "ge": 934, "bg": 996, "fi": 546, "ch": 723, "xn--80aswg": 221, "center": 1251, "art": 660, "tk": 893, "ec": 297, "ml": 297, "hu": 157, "hk": 142, "city": 1064, "casa": 46, "museum": 73, "ac": 107, "dev": 168, "flowers": 49, "plus": 557, "int": 114, "fun": 1433, "gov": 113, "dog": 104, "team": 406, "xn--80asehdb": 558, "re": 146, "ng": 179, "la": 171, "digital": 271, "tech": 810, "wiki": 598, "pw": 1014, "stream": 310, "website": 786, "ma": 195, "ph": 1026, "business": 65, "xn--j1amh": 444, "rent": 156, "link": 420, "ms": 164, "jp": 361, "hr": 121, "li": 74, "xn--p1acf": 1124, "RU": 31, "live": 1503, "ga": 139, "film": 87, "komatsu": 2, "review": 78, "day": 146, "blog": 977, "group": 544, "be": 1806, "parts": 101, "so": 385, "studio": 564, "zone": 235, "cam": 227, "radio": 25, "salon": 45, "do": 100, "express": 332, "vet": 66, "xn--d1acj3b": 177, "bz": 404, "beauty": 19, "tools": 121, "asia": 549, "photo": 113, "tours": 60, "il": 1264, "design": 224, "limited": 23, "uk": 465, "academy": 444, "help": 318, "games": 316, "global": 103, "ro": 269, "finance": 59, "tatar": 183, "vip": 661, "pics": 18, "ag": 267, "win": 460, "at": 347, "pub": 159, "company": 343, "hospital": 30, "ae": 154, "ltd": 131, "mn": 57, "sb": 36, "vn": 217, "best": 476, "pn": 85, "photos": 37, "id": 149, "cf": 84, "gq": 31, "mx": 38, "show": 169, "im": 318, "love": 210, "ooo": 241, "aero": 308, "cruises": 3, "promo": 133, "boutique": 50, "place": 63, "reviews": 42, "th": 29, "pt": 250, "bio": 94, "rest": 126, "lol": 55, "fashion": 25, "kitchen": 61, "report": 330, "ski": 33, "audio": 141, "world": 597, "berlin": 53, "doctor": 58, "men": 241, "restaurant": 12, "construction": 26, "clinic": 459, "fund": 44, "education": 134, "yachts": 8, "cyou": 303, "bet": 131, "solutions": 36, "vin": 65, "land": 329, "basketball": 49, "memorial": 33, "dk": 136, "fish": 176, "energy": 113, "football": 86, "work": 421, "house": 138, "watch": 138, "st": 38, "edu": 174, "sx": 31, "farm": 117, "rocks": 52, "taxi": 131, "cool": 161, "rehab": 14, "ly": 32, "ar": 64, "university": 51, "host": 29, "style": 210, "fans": 100, "beer": 93, "fan": 247, "is": 226, "institute": 50, "family": 91, "bike": 49, "sy": 158, "red": 260, "quest": 12, "black": 7, "community": 62, "cafe": 109, "wine": 33, "shopping": 24, "sk": 153, "tn": 58, "lawyer": 4, "tokyo": 2, "nu": 64, "fishing": 17, "consulting": 47, "health": 29, "mg": 17, "careers": 14, "run": 179, "sa": 14, "gallery": 90, "fit": 46, "capital": 38, "works": 58, "tips": 99, "sex": 74, "network": 47, "study": 34, "moda": 102, "gift": 62, "cat": 66, "icu": 240, "coffee": 57, "dance": 28, "social": 127, "training": 15, "date": 100, "sbs": 31, "pizza": 17, "pk": 42, "br": 83, "cfd": 60, "kr": 116, "cloud": 92, "sg": 68, "ba": 13, "tf": 3, "cl": 148, "vc": 110, "porn": 26, "ink": 93, "technology": 26, "gold": 45, "no": 110, "dating": 81, "cx": 130, "auction": 5, "mk": 74, "delivery": 42, "buzz": 20, "ai": 152, "html": 9, "london": 20, "broker": 8, "party": 101, "llc": 9, "systems": 82, "loans": 83, "uno": 91, "eus": 1, "supply": 16, "ke": 42, "bingo": 26, "coop": 23, "africa": 43, "haus": 23, "realestate": 7, "tl": 14, "lc": 15, "money": 43, "wtf": 249, "dentist": 7, "bid": 91, "tennis": 22, "ist": 5, "credit": 7, "theater": 22, "gg": 86, "bond": 22, "support": 48, "shoes": 9, "moe": 21, "qa": 33, "services": 17, "cooking": 3, "pm": 14, "ir": 114, "yoga": 37, "chat": 33, "xn--c1avg": 78, "vg": 41, "mu": 12, "nf": 4, "camp": 49, "ie": 51, "marketing": 40, "engineering": 14, "racing": 4, "bar": 69, "hamburg": 16, "nz": 55, "dental": 56, "gifts": 33, "care": 18, "eco": 63, "florist": 10, "tr": 94, "pet": 77, "management": 12, "jewelry": 24, "au": 58, "bible": 8, "discount": 15, "tel": 20, "trade": 86, "archi": 3, "XN--P1AI": 7, "tc": 12, "srl": 1, "direct": 50, "monster": 24, "ky": 27, "realty": 25, "fitness": 42, "za": 30, "green": 8, "foundation": 11, "sport": 85, "lk": 33, "rip": 22, "cheap": 5, "hair": 22, "property": 6, "cash": 33, "gs": 6, "dj": 9, "equipment": 3, "surgery": 1, "ninja": 79, "pictures": 23, "forum": 1, "vote": 5, "insure": 11, "sr": 5, "villas": 5, "hockey": 20, "auto": 8, "rodeo": 11, "jobs": 24, "gal": 1, "cars": 4, "cu": 16, "band": 19, "gives": 5, "abbott": 4, "blue": 14, "mom": 24, "exchange": 11, "wedding": 13, "futbol": 8, "pe": 16, "kim": 19, "istanbul": 2, "college": 9, "mba": 30, "kp": 7, "shell": 2, "koeln": 6, "ci": 1, "observer": 1, "webcam": 7, "codes": 6, "law": 19, "cm": 1, "zw": 11, "miami": 5, "events": 40, "ventures": 15, "amsterdam": 4, "uy": 6, "car": 11, "surf": 2, "adult": 19, "town": 28, "lighting": 17, "sh": 18, "casino": 16, "limo": 6, "sc": 7, "cg": 1, "golf": 4, "tax": 7, "catering": 17, "contact": 4, "lu": 13, "bo": 2, "ovh": 26, "international": 11, "garden": 8, "furniture": 9, "partners": 22, "graphics": 8, "camera": 2, "my": 28, "tube": 16, "onl": 9, "ps": 2, "spa": 1, "industries": 3, "church": 38, "nrw": 3, "build": 5, "repair": 21, "glass": 4, "pa": 1, "domains": 1, "page": 12, "mc": 13, "coach": 3, "va": 21, "horse": 9, "email": 5, "engineer": 2, "voyage": 6, "ceo": 1, "bi": 4, "gl": 1, "vodka": 7, "swiss": 1, "sandvik": 2, "ug": 18, "solar": 9, "yt": 5, "as": 4, "charity": 2, "loan": 14, "investments": 14, "sexy": 8, "paris": 2, "gy": 1, "yandex": 10, "jo": 2, "bd": 1, "bm": 2, "actor": 9, "clothing": 4, "dm": 1, "nyc": 6, "immo": 3, "al": 12, "barcelona": 2, "properties": 3, "ngo": 8, "bj": 1, "homes": 1, "sn": 2, "af": 1, "hn": 4, "computer": 1, "ht": 16, "dhl": 1, "software": 4, "army": 11, "ve": 1, "aq": 1, "game": 5, "cd": 2, "cards": 4, "mz": 1, "weber": 1, "wf": 4, "gd": 4, "dz": 1, "gw": 1, "lb": 1, "canon": 1, "luxury": 5, "cab": 6, "country": 1, "eg": 3, "bank": 1, "luxe": 1, "bot": 1, "saxo": 1, "mp": 2, "gt": 3, "democrat": 5, "gp": 1, "ad": 2, "kh": 1, "holiday": 1, "earth": 3, "desi": 1, "py": 6, "photography": 5, "np": 5, "xxx": 1, "deals": 3, "rw": 4, "trading": 1, "rentals": 1, "directory": 1, "coupons": 1, "tz": 1, "vegas": 1, "courses": 1, "sony": 2, "vacations": 1, "recipes": 1, "gh": 1, "xn--80ao21a": 2, "baby": 1, "wales": 2, "mo": 2, "pink": 1, "attorney": 1, "ni": 1, "soy": 1, "php": 1, "cleaning": 5, "productions": 1}