{"com": 3920053, "bz": 627, "pt": 704, "org": 188199, "ca": 100440, "club": 285994, "br": 4680, "au": 162119, "cc": 9156, "gov": 5376, "church": 1141, "cn": 17821, "build": 93, "nl": 5780, "biz": 39292, "net": 22287, "cl": 981, "info": 71784, "int": 121, "it": 4532, "uk": 157945, "pictures": 30, "pro": 10039, "xyz": 4607, "me": 13252, "za": 12657, "xxx": 934, "nz": 11084, "in": 24874, "xn--p1ai": 334, "computer": 135, "website": 2991, "ch": 8325, "life": 3284, "fr": 6360, "de": 22518, "co": 27597, "ie": 10966, "fi": 1434, "bid": 10269, "vn": 1004, "us": 19092, "sg": 4926, "si": 465, "ph": 2913, "eu": 18720, "dk": 3674, "tk": 1997, "se": 4559, "asia": 3682, "pl": 3531, "vegas": 51, "rodeo": 1, "ws": 469, "th": 492, "space": 1663, "services": 316, "kr": 1222, "ru": 1254, "cz": 2729, "jp": 2896, "lt": 597, "edu": 7484, "at": 4452, "al": 342, "by": 457, "tv": 3686, "cloud": 669, "be": 7463, "ink": 76, "my": 4113, "cm": 206, "name": 520, "hu": 1394, "pw": 461, "io": 2662, "top": 4068, "pk": 1777, "kz": 173, "coffee": 184, "shop": 598, "place": 45, "st": 58, "quebec": 6, "tw": 751, "es": 3912, "mobi": 1521, "ng": 1224, "tr": 729, "blog": 15517, "design": 630, "hk": 3073, "farm": 119, "lv": 521, "id": 1012, "ml": 299, "mx": 682, "ae": 4865, "parts": 27, "coop": 417, "chat": 142, "online": 5902, "link": 274, "trade": 1564, "one": 2056, "ua": 1308, "today": 705, "tech": 1639, "systems": 68, "ug": 228, "stream": 698, "diamonds": 10, "download": 274, "ee": 605, "bd": 759, "bzh": 19, "care": 274, "bg": 1046, "men": 1339, "camera": 66, "capital": 71, "ar": 1190, "blue": 162, "cam": 253, "ir": 785, "band": 240, "cafe": 81, "academy": 444, "live": 601, "cash": 327, "black": 61, "cat": 956, "africa": 319, "am": 1037, "guru": 361, "no": 1373, "ge": 300, "earth": 58, "gr": 2746, "click": 554, "center": 822, "sk": 614, "gq": 172, "is": 672, "ai": 245, "news": 1075, "na": 65, "nf": 5, "win": 1483, "az": 626, "boutique": 224, "berlin": 171, "builders": 52, "site": 3554, "company": 625, "casino": 61, "bt": 114, "city": 370, "bs": 34, "brussels": 73, "cf": 530, "codes": 115, "store": 1091, "bio": 110, "beer": 158, "camp": 76, "careers": 57, "clinic": 97, "cars": 5, "bar": 59, "work": 246, "zone": 158, "world": 1202, "aero": 381, "agency": 710, "ag": 183, "amsterdam": 140, "zw": 123, "art": 579, "vip": 311, "domains": 151, "hitachi": 3, "associates": 88, "toys": 12, "af": 163, "ac": 144, "accountant": 462, "as": 82, "webcam": 423, "run": 44, "cy": 257, "bike": 305, "ba": 390, "bargains": 172, "training": 73, "buzz": 218, "hr": 463, "php": 44, "bb": 105, "cool": 308, "international": 98, "expert": 148, "guide": 252, "review": 1267, "ro": 1781, "lk": 568, "london": 469, "mt": 163, "sh": 41, "digital": 199, "cd": 96, "ve": 35, "foundation": 81, "ke": 1036, "jm": 87, "bw": 85, "law": 96, "corsica": 4, "dental": 43, "ninja": 189, "loan": 296, "porn": 224, "mn": 122, "games": 94, "np": 364, "ms": 27, "ltd": 176, "kyoto": 4, "holiday": 22, "media": 366, "ga": 699, "lighting": 28, "md": 173, "mk": 265, "network": 218, "kiwi": 63, "mw": 37, "global": 271, "lb": 98, "land": 65, "love": 78, "physio": 14, "ly": 121, "photography": 366, "press": 1264, "legal": 63, "mu": 100, "nu": 360, "lc": 18, "pub": 64, "mm": 41, "jobs": 79, "realtor": 286, "pe": 204, "scot": 192, "fo": 31, "sexy": 413, "education": 311, "auto": 8, "fm": 8145, "do": 49, "capetown": 107, "tours": 62, "bi": 74, "travel": 288, "cards": 43, "pm": 25, "cab": 20, "studio": 204, "lu": 212, "photo": 189, "rs": 361, "yoga": 53, "gallery": 148, "help": 40, "nyc": 349, "juegos": 1, "gd": 18, "eg": 166, "events": 162, "faith": 98, "fail": 22, "party": 933, "cheap": 86, "mil": 112, "ovh": 114, "express": 65, "reviews": 133, "tube": 87, "college": 83, "business": 430, "date": 217, "il": 792, "bo": 51, "enterprises": 25, "dog": 67, "dm": 27, "fj": 127, "consulting": 171, "film": 51, "wales": 174, "viajes": 2, "wang": 17, "uz": 83, "uno": 39, "vi": 6, "wedding": 129, "community": 267, "gal": 25, "to": 6, "bm": 221, "software": 78, "rocks": 313, "feedback": 21, "estate": 33, "email": 60, "tz": 140, "dance": 100, "dj": 27, "directory": 142, "construction": 69, "tools": 81, "sa": 197, "gold": 17, "town": 20, "vc": 38, "pink": 41, "htm": 8, "best": 51, "photos": 116, "host": 945, "furniture": 13, "ooo": 23, "pics": 221, "mom": 9, "wine": 37, "adult": 79, "joburg": 30, "canon": 5, "group": 273, "ma": 49, "marketing": 86, "sex": 86, "army": 11, "pg": 35, "wtf": 69, "wiki": 48, "video": 257, "voyage": 6, "watch": 44, "vg": 35, "ventures": 39, "vet": 35, "eus": 36, "onl": 6, "audio": 137, "bet": 45, "support": 40, "surgery": 5, "solutions": 294, "tips": 160, "la": 147, "energy": 56, "cymru": 96, "cruises": 6, "deals": 69, "restaurant": 29, "red": 45, "okinawa": 3, "paris": 17, "rw": 48, "re": 47, "mp": 39, "casa": 27, "science": 848, "accountants": 24, "football": 33, "kh": 111, "equipment": 32, "plus": 40, "diet": 4, "melbourne": 59, "racing": 181, "plumbing": 13, "sydney": 34, "gg": 122, "im": 169, "sb": 7, "coach": 82, "discount": 22, "html": 33, "ck": 19, "market": 59, "dz": 8, "report": 53, "gh": 114, "works": 82, "ong": 6, "mo": 23, "gy": 30, "bank": 177, "clothing": 94, "catering": 48, "partners": 27, "rentals": 33, "lr": 14, "miami": 22, "management": 20, "kg": 50, "fit": 93, "lawyer": 41, "moe": 62, "money": 31, "mc": 18, "ngo": 42, "moscow": 22, "dating": 24, "cu": 5, "desi": 332, "direct": 75, "cx": 63, "fun": 287, "gi": 50, "hosting": 21, "bh": 107, "recipes": 29, "house": 91, "koeln": 5, "archi": 39, "contractors": 17, "exchange": 20, "sc": 43, "dev": 7, "ky": 62, "cern": 28, "bn": 41, "auction": 15, "ad": 23, "li": 99, "properties": 69, "apartments": 18, "social": 79, "rent": 13, "uy": 51, "jo": 97, "lol": 98, "tt": 64, "team": 36, "healthcare": 37, "shopping": 6, "sale": 13, "zm": 24, "om": 27, "shiksha": 7, "gt": 41, "blackfriday": 15, "claims": 11, "tirol": 7, "family": 50, "durban": 12, "graphics": 58, "sv": 3, "fitness": 75, "style": 51, "su": 17, "technology": 156, "attorney": 67, "actor": 12, "yachts": 5, "sn": 14, "ismaili": 5, "boats": 1, "xin": 13, "mv": 50, "kim": 40, "je": 48, "institute": 87, "istanbul": 11, "health": 29, "kw": 41, "aspx": 11, "engineering": 33, "makeup": 1, "menu": 14, "gop": 14, "kaufen": 2, "komatsu": 2, "rip": 13, "pr": 6, "investments": 9, "xn--czr694b": 2, "cr": 40, "vu": 35, "google": 12, "doctor": 11, "loans": 75, "glass": 17, "sl": 56, "cleaning": 43, "kitchen": 50, "cricket": 222, "forsale": 19, "tm": 8, "aq": 13, "afl": 23, "va": 6, "ni": 4, "ps": 54, "tc": 9, "rest": 6, "tokyo": 94, "tax": 22, "shoes": 7, "sx": 10, "study": 8, "vacations": 11, "ec": 113, "crs": 1, "show": 42, "navy": 3, "immo": 5, "gs": 30, "condos": 19, "cooking": 24, "qa": 112, "irish": 15, "golf": 56, "hn": 7, "xn--mk1bu44c": 1, "museum": 14, "dentist": 18, "industries": 11, "fyi": 92, "boston": 10, "fishing": 14, "property": 40, "vin": 7, "xn--p1acf": 4, "pa": 13, "ski": 8, "holdings": 10, "wien": 5, "insure": 18, "fund": 21, "villas": 8, "gifts": 28, "supply": 15, "pizza": 20, "pet": 19, "jewelry": 14, "hamburg": 23, "jpg": 5, "ttff": 1, "career": 3, "pharmacy": 18, "py": 11, "moda": 5, "gl": 17, "fish": 27, "finance": 27, "gm": 14, "haus": 17, "flowers": 8, "school": 80, "coupons": 15, "limo": 17, "how": 23, "university": 28, "wf": 2, "tennis": 8, "hm": 1, "asp": 2, "country": 22, "organic": 2, "movie": 34, "cancerresearch": 4, "fashion": 25, "hoteles": 12, "vision": 27, "engineer": 16, "florist": 11, "ht": 7, "xn--j1amh": 3, "xn--kput3i": 1, "hockey": 11, "exposed": 20, "rehab": 8, "schule": 5, "swiss": 30, "cologne": 8, "ao": 8, "alsace": 6, "et": 31, "tel": 53, "bible": 36, "ceo": 4, "icu": 25, "sy": 12, "barcelona": 22, "delivery": 9, "krd": 7, "gift": 20, "radio": 9, "eco": 14, "gmbh": 11, "ico": 8, "gratis": 4, "so": 25, "tf": 10, "mz": 4, "limited": 28, "tl": 6, "green": 23, "gives": 5, "horse": 12, "solar": 16, "motorcycles": 11, "cv": 5, "taxi": 9, "ist": 15, "game": 8, "pictet": 1, "srl": 3, "degree": 2, "ci": 13, "maison": 2, "repair": 22, "gu": 6, "app": 17, "productions": 34, "ax": 13, "lgbt": 14, "abbott": 3, "nrw": 2, "vlaanderen": 1, "bayern": 10, "car": 2, "courses": 7, "observer": 6, "ren": 5, "tn": 12, "republican": 1, "credit": 7, "reisen": 7, "xn--fiqs8s": 1, "mba": 5, "woff": 1, "sr": 2, "promo": 13, "poker": 4, "neustar": 1, "kn": 4, "bnpparibas": 7, "inet": 1, "financial": 10, "lat": 2, "sony": 3, "garden": 11, "sd": 10, "basketball": 15, "gent": 9, "ls": 6, "tj": 13, "soy": 2, "jcb": 1, "supplies": 17, "bauhaus": 1, "axa": 1, "insurance": 2, "sm": 3, "salon": 9, "cg": 4, "nc": 6, "jetzt": 5, "bot": 3, "mg": 5, "flights": 11, "nagoya": 4, "erni": 1, "soccer": 15, "fage": 2, "saxo": 7, "trust": 5, "tattoo": 7, "pf": 8, "cw": 8, "xn--80asehdb": 3, "sz": 12, "hiphop": 3, "hiv": 2, "hospital": 1, "lease": 5, "ki": 4, "saarland": 2, "sbi": 2, "christmas": 10, "memorial": 2, "fans": 5, "iq": 11, "sncf": 2, "gdn": 3, "kpmg": 2, "surf": 2, "theater": 3, "vistaprint": 1, "seat": 1, "singles": 4, "realty": 3, "nr": 3, "guitars": 4, "tires": 1, "aw": 9, "sucks": 1, "mortgage": 7, "yt": 3, "realestate": 1, "xn--ses554g": 3, "mr": 1, "rugby": 1, "gp": 2, "stockholm": 1, "tg": 59, "bf": 3, "bj": 2, "airforce": 3, "compare": 1, "rio": 2, "vote": 2, "honda": 1, "cgi": 3, "xn--80aswg": 1, "xn--6frz82g": 1, "swf": 1, "homes": 1, "creditcard": 1, "PHP": 1, "luxury": 3, "frl": 2, "auspost": 1, "bingo": 3, "post": 1, "taipei": 3, "shriram": 2, "storage": 1, "2id0183248635": 1, "forex": 2, "tatar": 2, "xn--80adxhks": 1, "kred": 1, "reise": 2, "ruhr": 1, "vodka": 2, "JPG": 1, "sandvik": 1, "hisamitsu": 1, "qpon": 1, "baby": 1, "gn": 1, "gw": 1, "fox": 1, "xn--ngbc5azd": 1, "barclays": 1, "ikano": 1, "democrat": 1, "jsp": 1, "aco": 1, "trading": 1}