{"hk": 33243, "com": 419639, "tw": 783876, "org": 194223, "net": 73195, "my": 996, "edu": 771, "cn": 6049, "mo": 390, "info": 2406, "za": 32, "to": 1057, "cc": 5019, "ch": 558, "me": 837, "jp": 1879, "us": 740, "asia": 282, "ca": 583, "ws": 293, "biz": 523, "au": 226, "uk": 546, "sx": 2, "name": 70, "gov": 451, "mobi": 74, "th": 37, "mu": 5, "fm": 122, "de": 161, "nz": 26, "st": 42, "va": 19, "es": 39, "tv": 881, "co": 106, "pw": 233, "in": 75, "it": 50, "am": 2, "kr": 56, "nl": 27, "ml": 16, "gd": 24, "cx": 6, "no": 7, "fr": 81, "sh": 3, "ro": 63, "museum": 15, "ph": 13, "pro": 15, "dj": 192, "moe": 5, "cz": 18, "sg": 33, "re": 1, "xn--j6w193g": 1, "gp": 1, "io": 46, "at": 21, "gl": 7, "eu": 20, "hu": 5, "travel": 18, "cl": 9, "mx": 5, "be": 57, "br": 64, "se": 20, "vn": 15, "nu": 14, "tk": 48, "ru": 33, "la": 100, "tc": 27, "ms": 2, "vc": 3, "ve": 4, "il": 9, "cm": 4, "is": 8, "today": 12, "pl": 12, "int": 11, "xxx": 4, "ar": 5, "tr": 13, "ee": 2, "ly": 34, "fi": 3, "im": 8, "xyz": 2, "ir": 4, "gr": 7, "do": 5, "pt": 5, "pe": 1, "ua": 12, "html": 1, "lv": 10, "dk": 2, "ie": 2, "gg": 6, "id": 3, "so": 3, "aero": 6, "mv": 1, "rs": 1, "coop": 1, "vu": 6, "gs": 3, "bz": 2, "wf": 1, "ma": 3, "lu": 1, "sc": 1, "php": 2, "tf": 2, "by": 1, "uy": 1, "np": 1, "ae": 1, "sk": 2, "bh": 1, "su": 1, "pk": 7, "tm": 1, "mt": 1, "taipei": 41, "club": 2, "eg": 1}