{"com": 2804089, "au": 199999, "fi": 3040, "co": 20054, "org": 365807, "io": 14835, "eu": 18557, "news": 5684, "online": 3647, "net": 152708, "nz": 41851, "tours": 40, "nl": 19402, "in": 40594, "ir": 2124, "edu": 74930, "uk": 480380, "se": 6103, "one": 775, "gov": 18696, "tips": 350, "info": 29831, "ca": 58966, "ro": 3372, "ru": 11004, "gr": 4037, "us": 17256, "za": 41059, "by": 308, "tj": 69, "ee": 1458, "travel": 618, "app": 23993, "tv": 8241, "bg": 694, "no": 3151, "my": 5351, "video": 310, "top": 3486, "ai": 1572, "om": 60, "int": 1131, "ch": 8817, "fr": 16312, "site": 2336, "pk": 5676, "pl": 32739, "estate": 31, "blog": 6278, "cc": 3602, "game": 24, "bd": 911, "ink": 177, "es": 10295, "tech": 941, "br": 7068, "help": 233, "kr": 1909, "fm": 4316, "jp": 7467, "sg": 5725, "dk": 3531, "vn": 3461, "hr": 1131, "mu": 211, "ua": 3189, "rest": 84, "de": 29664, "be": 7081, "cat": 972, "ph": 5326, "health": 184, "host": 73, "ie": 18246, "website": 707, "africa": 672, "life": 1014, "ae": 2947, "win": 911, "cf": 233, "coop": 443, "sex": 220, "agency": 362, "asia": 1432, "monster": 188, "ng": 7817, "gh": 646, "pt": 1626, "id": 4236, "wine": 106, "me": 9292, "pro": 2993, "directory": 181, "biz": 7243, "design": 382, "gm": 122, "ly": 683, "cafe": 161, "xyz": 6193, "ug": 1020, "today": 1510, "il": 3059, "club": 3827, "tr": 3014, "ovh": 42, "link": 740, "shop": 2654, "cn": 5693, "construction": 10, "hk": 3436, "cz": 8211, "im": 366, "ninja": 192, "mobi": 1681, "it": 15153, "pics": 119, "ky": 119, "store": 1761, "lt": 1064, "army": 16, "llc": 22, "scot": 893, "taxi": 13, "tw": 2921, "fashion": 63, "lighting": 19, "ke": 3504, "at": 3173, "photo": 65, "am": 898, "is": 1348, "lv": 897, "th": 2600, "pw": 881, "buzz": 946, "finance": 155, "fun": 601, "rs": 1402, "icu": 333, "mx": 1592, "vip": 641, "bz": 305, "live": 1796, "ge": 615, "lk": 1635, "pub": 291, "ws": 771, "su": 569, "eus": 202, "network": 542, "games": 316, "wales": 582, "work": 308, "land": 117, "dance": 33, "sh": 155, "mt": 582, "cl": 1160, "lb": 170, "art": 806, "sa": 600, "photography": 209, "ar": 984, "golf": 40, "bar": 324, "tz": 279, "world": 1095, "onl": 215, "hu": 2382, "zw": 941, "markets": 23, "sk": 1253, "expert": 66, "mil": 925, "sb": 23, "uy": 77, "stream": 234, "nu": 1284, "ps": 168, "glass": 39, "to": 1177, "si": 1049, "farm": 95, "money": 69, "repair": 29, "equipment": 12, "lu": 604, "legal": 66, "bo": 98, "bio": 126, "group": 266, "wiki": 841, "ngo": 95, "tl": 137, "business": 91, "dev": 1402, "az": 626, "jobs": 327, "marketing": 101, "radio": 84, "bh": 127, "wang": 16, "uz": 150, "bid": 34, "academy": 321, "guide": 327, "sport": 78, "watch": 176, "codes": 143, "cy": 526, "care": 136, "cloud": 531, "aero": 326, "realtor": 119, "reviews": 214, "gg": 833, "boutique": 91, "gallery": 186, "bank": 60, "vegas": 34, "show": 82, "bm": 146, "ma": 200, "bzh": 21, "works": 121, "kz": 607, "bn": 102, "ga": 297, "sm": 53, "np": 433, "dating": 56, "dog": 44, "cymru": 109, "social": 430, "school": 165, "media": 969, "space": 817, "cash": 121, "surf": 31, "coffee": 98, "quest": 41, "exchange": 63, "name": 702, "al": 323, "fyi": 95, "nyc": 436, "re": 147, "christmas": 8, "eg": 529, "exposed": 14, "webcam": 109, "press": 422, "st": 344, "jo": 157, "gal": 57, "inc": 16, "jm": 138, "events": 161, "amsterdam": 53, "observer": 28, "kiwi": 77, "domains": 32, "moe": 112, "global": 480, "foundation": 100, "community": 362, "tk": 395, "pg": 159, "xn--p1ai": 182, "best": 333, "ag": 179, "church": 504, "tc": 75, "ms": 146, "trading": 12, "deals": 231, "movie": 59, "fan": 45, "cam": 257, "qa": 377, "tube": 205, "tn": 139, "yt": 20, "kw": 269, "auction": 35, "london": 399, "center": 160, "vc": 245, "bt": 136, "bike": 89, "cx": 113, "consulting": 91, "gn": 13, "museum": 144, "technology": 133, "bs": 45, "gold": 17, "studio": 304, "ec": 121, "bet": 81, "digital": 309, "realestate": 58, "casa": 57, "cfd": 26, "cw": 14, "boston": 3, "men": 46, "gy": 133, "download": 124, "hn": 40, "garden": 32, "google": 19, "report": 307, "gq": 148, "vu": 85, "va": 54, "lol": 114, "gmbh": 7, "chat": 99, "sony": 2, "aws": 37, "porn": 80, "mw": 182, "productions": 31, "fit": 126, "zm": 85, "la": 436, "fj": 176, "ht": 95, "brussels": 55, "rocks": 378, "team": 83, "tokyo": 136, "camp": 62, "international": 99, "city": 339, "clothing": 75, "adult": 72, "earth": 113, "li": 136, "dentist": 9, "et": 74, "party": 114, "guru": 389, "support": 89, "ba": 207, "zone": 355, "iq": 128, "style": 72, "ml": 175, "cr": 116, "ltd": 126, "cyou": 171, "mn": 146, "cu": 91, "software": 69, "courses": 32, "alsace": 16, "sydney": 65, "limited": 20, "law": 249, "dz": 52, "capital": 41, "page": 210, "bb": 108, "solutions": 290, "pe": 311, "mk": 414, "ao": 9, "xxx": 98, "audio": 144, "wien": 11, "associates": 3, "bnpparibas": 29, "melbourne": 50, "film": 46, "systems": 70, "gt": 47, "town": 75, "ikano": 2, "mo": 128, "ntt": 16, "pm": 179, "swiss": 66, "ve": 54, "tools": 113, "do": 102, "na": 305, "cv": 32, "so": 155, "education": 182, "af": 158, "run": 134, "services": 85, "mv": 125, "pictures": 45, "red": 68, "express": 42, "shiksha": 12, "pr": 41, "love": 129, "vision": 33, "training": 67, "recipes": 118, "football": 47, "md": 389, "vet": 33, "physio": 17, "gi": 66, "cricket": 22, "miami": 29, "plus": 152, "je": 166, "day": 12, "as": 63, "ls": 36, "email": 53, "ventures": 28, "mz": 51, "kim": 39, "kpmg": 128, "yoga": 35, "company": 93, "weir": 2, "mm": 161, "mg": 21, "discount": 18, "rugby": 45, "dj": 19, "house": 100, "builders": 80, "sexy": 21, "ck": 9, "graphics": 40, "ax": 3, "fo": 59, "ooo": 54, "sc": 93, "mom": 36, "wtf": 103, "tt": 169, "gent": 6, "hiphop": 6, "solar": 37, "trade": 68, "nrw": 10, "direct": 97, "pizza": 13, "paris": 59, "jewelry": 17, "delivery": 32, "diamonds": 14, "shoes": 23, "photos": 113, "kp": 4, "racing": 14, "cern": 39, "sr": 10, "mr": 5, "fish": 27, "kh": 109, "shopping": 41, "lc": 13, "wf": 8, "rw": 113, "bingo": 8, "fitness": 60, "cooking": 21, "eco": 67, "supplies": 15, "family": 42, "gift": 45, "science": 119, "band": 30, "krd": 33, "clinic": 33, "careers": 102, "limo": 3, "moscow": 24, "build": 20, "tf": 35, "mba": 36, "toys": 39, "immo": 13, "coach": 38, "mc": 43, "mortgage": 3, "guitars": 12, "engineering": 17, "uno": 55, "fishing": 9, "canon": 34, "accountants": 3, "berlin": 82, "saxo": 95, "gs": 27, "energy": 73, "lawyer": 19, "lgbt": 62, "healthcare": 39, "sharp": 3, "date": 37, "green": 32, "attorney": 11, "vg": 65, "soccer": 9, "click": 106, "sale": 72, "review": 59, "bw": 88, "kg": 65, "wedding": 62, "tickets": 10, "joburg": 14, "aw": 4, "pink": 18, "market": 142, "ci": 22, "industries": 7, "sd": 56, "gd": 54, "sv": 30, "irish": 32, "bargains": 16, "fans": 17, "college": 34, "cards": 52, "desi": 17, "sbs": 32, "faith": 12, "gop": 16, "place": 52, "beauty": 15, "sy": 122, "property": 19, "hospital": 1, "how": 45, "sl": 37, "ye": 12, "fund": 31, "basketball": 29, "lr": 17, "durban": 6, "coupons": 20, "institute": 64, "ad": 36, "ac": 88, "tm": 45, "cm": 59, "gay": 8, "vi": 13, "realty": 8, "gp": 3, "bible": 17, "py": 39, "kitchen": 40, "tax": 18, "university": 39, "gratis": 4, "sx": 20, "luxury": 10, "taipei": 19, "villas": 8, "php": 7, "hamburg": 4, "kn": 10, "ismaili": 8, "voyage": 13, "forum": 25, "tattoo": 13, "rent": 17, "parts": 32, "investments": 9, "menu": 45, "dm": 14, "frl": 1, "contractors": 6, "insure": 19, "ski": 24, "rodeo": 21, "forsale": 45, "nc": 15, "gifts": 43, "inet": 1, "beer": 60, "vote": 11, "rehab": 24, "restaurant": 17, "lat": 10, "skin": 6, "cpa": 38, "furniture": 39, "plumbing": 5, "gl": 28, "capetown": 24, "cars": 13, "bayern": 21, "pa": 42, "hosting": 10, "NET": 4, "ki": 3, "xn--fpcrj9c3d": 2, "html": 12, "vin": 19, "fail": 5, "nec": 1, "dental": 25, "properties": 57, "homes": 22, "tirol": 15, "istanbul": 5, "hockey": 12, "weber": 6, "pf": 4, "blackfriday": 3, "memorial": 7, "gdn": 5, "rip": 17, "aq": 6, "actor": 19, "hiv": 1, "sandvik": 14, "career": 4, "bi": 12, "promo": 6, "casino": 39, "pet": 36, "bond": 7, "uol": 1, "charity": 7, "abbott": 6, "mp": 4, "vlaanderen": 2, "forex": 3, "kyoto": 6, "soy": 4, "holiday": 17, "yachts": 2, "horse": 6, "vacations": 8, "sn": 18, "sz": 25, "ist": 13, "saarland": 9, "blue": 42, "cab": 2, "fk": 5, "reisen": 1, "partners": 17, "rentals": 16, "xn--80asehdb": 4, "COM": 12, "gf": 1, "democrat": 1, "cool": 69, "xn--e1a4c": 1, "doctor": 7, "salon": 14, "schwarz": 1, "management": 7, "nf": 4, "archi": 7, "cd": 20, "flights": 6, "toshiba": 3, "koeln": 1, "enterprises": 19, "rio": 1, "seat": 4, "quebec": 13, "aspx": 6, "abudhabi": 15, "tienda": 7, "abb": 2, "camera": 2, "ong": 4, "tel": 17, "supply": 17, "kpn": 2, "afl": 9, "florist": 3, "cleaning": 3, "neustar": 1, "bj": 3, "tg": 5, "baby": 8, "catering": 3, "corsica": 3, "hair": 12, "kred": 5, "accountant": 2, "dhl": 1, "organic": 3, "xn--90ais": 3, "erni": 1, "cruises": 3, "apartments": 2, "ni": 20, "motorcycles": 6, "computer": 10, "auto": 8, "haus": 9, "pictet": 2, "tires": 1, "loan": 4, "singles": 5, "youtube": 4, "htm": 2, "loans": 3, "engineer": 12, "aquarelle": 8, "black": 8, "hitachi": 2, "futbol": 2, "financial": 10, "barcelona": 6, "sener": 1, "schule": 2, "cheap": 5, "cologne": 4, "moda": 6, "cg": 1, "java": 1, "credit": 1, "juegos": 1, "security": 6, "pharmacy": 4, "study": 6, "reit": 2, "xn--p1acf": 1, "ceo": 6, "country": 5, "crs": 4, "ren": 3, "sky": 2, "condos": 3, "makeup": 1, "barclays": 6, "xn--tckwe": 3, "insurance": 1, "ORG": 3, "pn": 5, "diet": 3, "toyota": 2, "lease": 2, "sucks": 3, "osaka": 5, "citic": 1, "bot": 2, "xn--h2brj9c": 1, "navy": 2, "sanofi": 1, "sarl": 2, "vig": 1, "nagoya": 1, "yokohama": 1, "jetzt": 1, "gives": 1, "maison": 1, "stockholm": 1, "feedback": 4, "foo": 1, "teva": 1, "EDU": 1, "car": 1, "toray": 1, "madrid": 1, "degree": 1, "holdings": 5, "rich": 1, "REALTOR": 1, "xn--6frz82g": 1, "praxi": 1, "gu": 2, "cancerresearch": 1, "theater": 1, "surgery": 1, "panasonic": 1, "med": 1, "xn--j1amh": 1, "td": 1}