{"com": 4142221, "uk": 143850, "net": 157011, "org": 376181, "ie": 5432, "de": 4072, "br": 1337, "it": 2174, "au": 40311, "ca": 23877, "gov": 38323, "nz": 11066, "ph": 1336, "fm": 4337, "edu": 80388, "ch": 855, "info": 4895, "me": 4881, "cc": 1323, "us": 11657, "dk": 675, "ru": 829, "id": 365, "co": 2110, "vu": 630, "is": 942, "es": 1330, "in": 5022, "cn": 293, "nl": 1269, "vn": 147, "za": 4417, "mil": 2217, "fr": 1477, "lk": 203, "tv": 8764, "hr": 69, "biz": 2911, "lu": 63, "my": 807, "pt": 92, "int": 1343, "jp": 2472, "at": 1193, "se": 1056, "hk": 343, "tm": 393, "eu": 2919, "va": 122, "today": 174, "mobi": 202, "io": 974, "nu": 4289, "si": 90, "xxx": 189, "cat": 41, "to": 1148, "kr": 150, "edumailto": 66, "sg": 1030, "hu": 135, "name": 131, "ug": 68, "ag": 406, "ua": 36, "cd": 2, "tk": 188, "ro": 232, "il": 280, "no": 321, "gr": 150, "ws": 352, "tr": 63, "pl": 319, "rs": 102, "cz": 358, "ba": 9, "am": 139, "dj": 529, "pk": 782, "tl": 9, "cx": 39, "lb": 142, "coop": 253, "mu": 56, "tw": 278, "pw": 139, "ee": 48, "travel": 423, "aero": 65, "li": 39, "asia": 67, "al": 10, "cl": 104, "mx": 155, "lv": 57, "be": 792, "pro": 81, "ky": 20, "su": 37, "bw": 12, "ge": 75, "om": 13, "fi": 188, "la": 76, "eg": 48, "ke": 301, "et": 13, "bz": 49, "gh": 14, "af": 15, "ir": 63, "sn": 1, "np": 47, "mt": 54, "ninja": 14, "ar": 99, "ae": 264, "ls": 3, "ma": 4, "sk": 40, "museum": 84, "az": 105, "tel": 4, "re": 18, "do": 85, "kz": 23, "gt": 2, "jobs": 36, "ly": 192, "tt": 63, "sx": 9, "sc": 15, "gy": 4, "pr": 4, "ng": 65, "cm": 28, "gs": 59, "agency": 1, "by": 18, "mw": 4, "bh": 2, "moe": 4, "commailto": 9, "zm": 7, "tj": 6, "directory": 3, "bm": 15, "im": 65, "bike": 1, "th": 60, "mn": 21, "st": 20, "bg": 36, "bo": 2, "fj": 9, "lt": 41, "cy": 6, "kg": 1, "qa": 21, "wf": 21, "kw": 9, "sa": 53, "md": 25, "rw": 14, "vg": 3, "tz": 15, "cool": 1, "na": 21, "gi": 5, "ms": 9, "ink": 1, "gg": 9, "bd": 32, "zw": 18, "ac": 16, "so": 7, "ps": 8, "ml": 12, "cu": 3, "jm": 9, "cr": 11, "cf": 1, "bn": 10, "ao": 3, "codes": 1, "estate": 2, "bb": 4, "mk": 12, "vc": 11, "uz": 5, "pe": 12, "nyc": 3, "sr": 1, "tc": 6, "photography": 3, "guru": 3, "ec": 1, "sz": 4, "mv": 5, "pics": 1, "iq": 2, "bt": 8, "kh": 2, "club": 6, "ht": 3, "sh": 12, "pa": 5, "ve": 5, "tf": 6, "jo": 11, "an": 1, "dm": 2, "gallery": 3, "sb": 1, "mm": 1, "sl": 1, "vi": 3, "pg": 5, "tn": 2, "sy": 3, "ai": 2, "yt": 2, "gl": 2, "systems": 1, "gd": 4, "pn": 2, "computer": 1, "php": 3, "sm": 1, "gm": 2, "kiwi": 1, "ki": 1, "fk": 1, "aq": 1, "ga": 2, "nr": 4, "photos": 2, "orgmailto": 1, "ck": 1, "mz": 1, "xyz": 4, "scot": 2, "report": 1, "govmailto": 1, "kn": 1, "berlin": 1}